actinia_grassdata_management_plugin/__init__.py
actinia_grassdata_management_plugin/endpoints.py
actinia_grassdata_management_plugin/wsgi.py
actinia_grassdata_management_plugin/core/__init__.py
actinia_grassdata_management_plugin/core/request_parser.py
actinia_grassdata_management_plugin/core/utils.py
actinia_grassdata_management_plugin/processing/__init__.py
actinia_grassdata_management_plugin/processing/actinia_processing/__init__.py
actinia_grassdata_management_plugin/processing/actinia_processing/ephemeral/__init__.py
actinia_grassdata_management_plugin/processing/actinia_processing/ephemeral/raster_colors.py
actinia_grassdata_management_plugin/processing/actinia_processing/ephemeral/raster_layer.py
actinia_grassdata_management_plugin/processing/actinia_processing/ephemeral/raster_legend.py
actinia_grassdata_management_plugin/processing/actinia_processing/ephemeral/vector_layer.py
actinia_grassdata_management_plugin/processing/actinia_processing/ephemeral/base/__init__.py
actinia_grassdata_management_plugin/processing/actinia_processing/ephemeral/base/renderer_base.py
actinia_grassdata_management_plugin/processing/actinia_processing/ephemeral_renderer_base/__init__.py
actinia_grassdata_management_plugin/processing/actinia_processing/ephemeral_renderer_base/raster_renderer.py
actinia_grassdata_management_plugin/processing/actinia_processing/ephemeral_renderer_base/strds_renderer.py
actinia_grassdata_management_plugin/processing/actinia_processing/ephemeral_renderer_base/vector_renderer.py
actinia_grassdata_management_plugin/processing/actinia_processing/persistent/__init__.py
actinia_grassdata_management_plugin/processing/actinia_processing/persistent/map_layer_management.py
actinia_grassdata_management_plugin/processing/actinia_processing/persistent/raster_colors.py
actinia_grassdata_management_plugin/processing/actinia_processing/persistent/raster_layer.py
actinia_grassdata_management_plugin/processing/actinia_processing/persistent/strds_management.py
actinia_grassdata_management_plugin-1.0.0.dist-info/licenses/LICENSE.txt
actinia_grassdata_management_plugin-1.0.0.dist-info/METADATA
actinia_grassdata_management_plugin-1.0.0.dist-info/WHEEL
actinia_grassdata_management_plugin-1.0.0.dist-info/top_level.txt
actinia_grassdata_management_plugin-1.0.0.dist-info/RECORD
