Metadata-Version: 2.4
Name: actinia-grassdata-management-plugin
Version: 1.0.0
Summary: An actinia-core plugin which adds vector- raster and STRDS enpoints to actinia-core
Author: Carmen Tawalika, Anika Weinmann, Guido Riembauer, Marc Jansen, Sören Gebbert, Markus Neteler, and more
License-Expression: GPL-3.0-or-later
Project-URL: Homepage, https://github.com/mundialis/actinia-grassdata-management-plugin
Project-URL: Tutorial, https://actinia-org.github.io/actinia-core
Project-URL: API_Docs, https://redocly.github.io/redoc/?url=https://actinia.mundialis.de/latest/swagger.json
Keywords: processing,earth observation,cloud-based processing,rest api,gis,grass gis,osgeo,data management
Classifier: Programming Language :: Python :: 3
Requires-Python: >=3.8
License-File: LICENSE.txt
Requires-Dist: actinia-api>=3.7.0
Requires-Dist: actinia-core>=6.0.1
Requires-Dist: actinia-rest-lib>=1.0.0
Requires-Dist: actinia-processing-lib>=1.1.0
Requires-Dist: Flask>=3.0.0
Requires-Dist: pwgen
Requires-Dist: setuptools==80.9.0
Requires-Dist: werkzeug>=3.1.3
Provides-Extra: test
Requires-Dist: pytest; extra == "test"
Requires-Dist: pytest-cov; extra == "test"
Dynamic: license-file
